AUTHORS
CHANGES
LICENSE.txt
MANIFEST.in
README.md
setup.py
feedly/__init__.py
feedly/activity.py
feedly/conftest.py
feedly/default_settings.py
feedly/exceptions.py
feedly/settings.py
feedly/tasks.py
feedly.egg-info/PKG-INFO
feedly.egg-info/SOURCES.txt
feedly.egg-info/dependency_links.txt
feedly.egg-info/not-zip-safe
feedly.egg-info/requires.txt
feedly.egg-info/top_level.txt
feedly/aggregators/__init__.py
feedly/aggregators/base.py
feedly/feed_managers/__init__.py
feedly/feed_managers/base.py
feedly/feeds/__init__.py
feedly/feeds/base.py
feedly/feeds/cassandra.py
feedly/feeds/memory.py
feedly/feeds/redis.py
feedly/feeds/aggregated_feed/__init__.py
feedly/feeds/aggregated_feed/base.py
feedly/feeds/aggregated_feed/cassandra.py
feedly/feeds/aggregated_feed/notification_feed.py
feedly/feeds/aggregated_feed/redis.py
feedly/metrics/__init__.py
feedly/metrics/base.py
feedly/metrics/python_statsd.py
feedly/metrics/statsd.py
feedly/serializers/__init__.py
feedly/serializers/activity_serializer.py
feedly/serializers/aggregated_activity_serializer.py
feedly/serializers/base.py
feedly/serializers/dummy.py
feedly/serializers/pickle_serializer.py
feedly/serializers/simple_timeline_serializer.py
feedly/serializers/utils.py
feedly/serializers/cassandra/__init__.py
feedly/serializers/cassandra/activity_serializer.py
feedly/serializers/cassandra/aggregated_activity_serializer.py
feedly/storage/__init__.py
feedly/storage/base.py
feedly/storage/memory.py
feedly/storage/cassandra/__init__.py
feedly/storage/cassandra/activity_storage.py
feedly/storage/cassandra/connection.py
feedly/storage/cassandra/models.py
feedly/storage/cassandra/timeline_storage.py
feedly/storage/hbase/__init__.py
feedly/storage/redis/__init__.py
feedly/storage/redis/activity_storage.py
feedly/storage/redis/connection.py
feedly/storage/redis/timeline_storage.py
feedly/storage/redis/structures/__init__.py
feedly/storage/redis/structures/base.py
feedly/storage/redis/structures/hash.py
feedly/storage/redis/structures/list.py
feedly/storage/redis/structures/sorted_set.py
feedly/tests/__init__.py
feedly/tests/activity.py
feedly/tests/serializers.py
feedly/tests/settings.py
