Metadata-Version: 1.1
Name: feedly
Version: 0.11.1
Summary: Feedly allows you to build complex feed and caching structures using Redis.
Home-page: http://github.com/tschellenbach/feedly
Author: Thierry Schellenbach
Author-email: thierryschellenbach@gmail.com
License: UNKNOWN
Platform: UNKNOWN
Classifier: Intended Audience :: Developers
Classifier: Intended Audience :: System Administrators
Classifier: Operating System :: OS Independent
Classifier: Topic :: Software Development
Classifier: Development Status :: 5 - Production/Stable
Classifier: License :: OSI Approved :: GNU General Public License (GPL)
Classifier: Natural Language :: English
Classifier: Programming Language :: Python
Classifier: Topic :: Scientific/Engineering :: Mathematics
Classifier: Topic :: Software Development :: Libraries :: Python Modules
Classifier: Framework :: Django
